onshape_robotics_toolkit/__init__.py
onshape_robotics_toolkit/config.py
onshape_robotics_toolkit/connect.py
onshape_robotics_toolkit/graph.py
onshape_robotics_toolkit/mesh.py
onshape_robotics_toolkit/parse.py
onshape_robotics_toolkit/robot.py
onshape_robotics_toolkit/words.txt
onshape_robotics_toolkit/formats/__init__.py
onshape_robotics_toolkit/formats/base.py
onshape_robotics_toolkit/formats/mjcf.py
onshape_robotics_toolkit/formats/urdf.py
onshape_robotics_toolkit/models/__init__.py
onshape_robotics_toolkit/models/assembly.py
onshape_robotics_toolkit/models/document.py
onshape_robotics_toolkit/models/element.py
onshape_robotics_toolkit/models/geometry.py
onshape_robotics_toolkit/models/joint.py
onshape_robotics_toolkit/models/link.py
onshape_robotics_toolkit/models/mass.py
onshape_robotics_toolkit/models/mjcf.py
onshape_robotics_toolkit/models/variable.py
onshape_robotics_toolkit/utilities/__init__.py
onshape_robotics_toolkit/utilities/helpers.py
onshape_robotics_toolkit-0.5.0.dist-info/METADATA
onshape_robotics_toolkit-0.5.0.dist-info/WHEEL
onshape_robotics_toolkit-0.5.0.dist-info/licenses/LICENSE.md
onshape_robotics_toolkit-0.5.0.dist-info/RECORD
