Metadata-Version: 2.4
Name: onshape-robotics-toolkit
Version: 0.5.0
Summary: A python library to facilitate interaction with Onshape's REST API
Project-URL: Repository, https://github.com/neurobionics/onshape-robotics-toolkit
Project-URL: Documentation, https://neurobionics.github.io/onshape-robotics-toolkit/
Author-email: Senthur Ayyappan <senthurayyappan@gmail.com>
License-File: LICENSE.md
Requires-Python: <4.0,>=3.10
Requires-Dist: loguru>=0.7.0
Requires-Dist: lxml>=5.3.0
Requires-Dist: matplotlib>=3.9.2
Requires-Dist: networkx>=3.4.2
Requires-Dist: numpy-stl>=3.1.2
Requires-Dist: numpy>=1.26.0
Requires-Dist: pillow>=10.0.0
Requires-Dist: pydantic>=2.9.2
Requires-Dist: python-dotenv>=1.0.1
Requires-Dist: pyyaml>=6.0.2
Requires-Dist: regex>=2024.9.11
Requires-Dist: requests>=2.32.3
Requires-Dist: scipy>=1.14.1
Requires-Dist: typing-extensions>=4.12.0
Provides-Extra: docs
Requires-Dist: mkdocs-material>=9.2.7; extra == 'docs'
Requires-Dist: mkdocs>=1.4.2; extra == 'docs'
Requires-Dist: mkdocstrings[python]>=0.26.1; extra == 'docs'
Requires-Dist: pymdown-extensions>=10.12; extra == 'docs'
Provides-Extra: simulation
Requires-Dist: mujoco>=3.3.7; extra == 'simulation'
Requires-Dist: optuna>=4.6.0; extra == 'simulation'
Requires-Dist: plotly>=6.5.0; extra == 'simulation'
Requires-Dist: usd-core>=25.11; extra == 'simulation'
